[{"paciente": "bruno", "especialidade": "pediatra", "data": "213123"}, {"paciente": "tester", "especialidade": "oftalmo", "data": "1231221"}, {"paciente": "cleitin", "especialidade": "pediatra", "data": "12313231"}, {"paciente": "bruno", "especialidade": "Oftalmologista", "data": "123"}, {"paciente": "bruno", "especialidade": "Cl\u00ednico Geral", "data": "21/09/2000"}, {"paciente": "guilherme", "especialidade": "Cl\u00ednico Geral", "data": "01/12/2023"}, {"paciente": "guilherme", "especialidade": "Oftalmologista", "data": "12312313"}, {"paciente": "guilherme", "especialidade": "Patologista", "data": "123213213"}, {"paciente": "rafael", "especialidade": "Cl\u00ednico Geral", "data": "01/12/2023"}, {"paciente": "rafel", "especialidade": "Patologista", "data": "12312313"}, {"paciente": "rafel", "especialidade": "Cl\u00ednico Geral", "data": "123123"}, {"paciente": "rafael", "especialidade": "Cl\u00ednico Geral", "data": "01/12/2023"}, {"paciente": "fagner", "especialidade": "Oftalmologista", "data": "232313"}, {"paciente": "fagner", "especialidade": "Oftalmologista", "data": "1231231"}, {"paciente": "fagner", "especialidade": "Oftalmologista", "data": "123123"}, {"paciente": "fagner2", "especialidade": "Patologista", "data": ""}, {"paciente": "fagner2", "especialidade": "Oftalmologista", "data": "312312313213"}, {"paciente": "Jos\u00e9", "especialidade": "Oftalmologista", "data": "01/01/2024"}]